{
    "access_dt": null,
    "attributes": null,
    "cite_metadata": null,
    "data_qualifier": null,
    "description": "ABSTRACT: The BOREAS RSS-14 team collected and processed several Level-1 GOES-7 and GOES-8 image data sets for 1994-1996, and GOES-7 Level-2 for 1994 over the BOREAS study region. This data set contains shortwave and longwave radiation images at the surface and top of the atmosphere derived from collected GOES-8 data. These GOES-8 Level-2 data cover the period from 12-Feb-1996 to 22-Oct-1996. There are images missing from the temporal series. The main difference between this data set and 1994 data set is in the spatial coverage and the grid cell size.",
    "description_attribution": "http://daac.ornl.gov//BOREAS/FollowOn/guides/hmet01_goes8-l2_96_doc.html",
    "doi": "10.3334/ORNLDAAC/605",
    "end_time": "1996-10-23T00:00:00",
    "href": "http://data.globalchange.gov/dataset/nasa-ornldaac-605.json",
    "identifier": "nasa-ornldaac-605",
    "lat_max": "60",
    "lat_min": "50",
    "lon_max": "-92",
    "lon_min": "-111",
    "name": "BOREAS Follow-On HMet-01 Level-2 GOES-8 1996 Shortwave and Longwave Radiation",
    "native_id": "hmet01_g8_l2",
    "processing_level": null,
    "publication_year": null,
    "release_dt": "2001-01-01T00:00:00",
    "scale": null,
    "scope": null,
    "spatial_extent": null,
    "spatial_ref_sys": null,
    "spatial_res": null,
    "start_time": "1996-02-12T00:00:00",
    "temporal_extent": null,
    "temporal_resolution": null,
    "type": null,
    "uri": "/dataset/nasa-ornldaac-605",
    "url": "http://daac.ornl.gov/cgi-bin/dsviewer.pl?ds_id=605",
    "variables": null,
    "version": null,
    "vertical_extent": null
}