{
    "href": "http://data.globalchange.gov/book/d75ec22c-95ef-4566-81bb-f13750f7e3fd.json",
    "identifier": "d75ec22c-95ef-4566-81bb-f13750f7e3fd",
    "in_library": null,
    "isbn": "978-0-309-14896-2",
    "number_of_pages": "598",
    "publisher": "National Research Council. The National Academies Press",
    "title": "Toward Sustainable Agricultural Systems in the 21st Century",
    "topic": null,
    "uri": "/book/d75ec22c-95ef-4566-81bb-f13750f7e3fd",
    "url": "http://www.nap.edu/catalog.php?record_id=12832",
    "year": "2010"
}