{
    "attrs": {
        ".reference_type": "0",
        "Author": "Mali, S.\rKachur, S.P.\rArguin, P.M.",
        "Issue": "SS02",
        "Journal": "Morbidity and Mortality Weekly Report",
        "Pages": "1-17",
        "Title": "Malaria surveillance\u2014United States, 2010",
        "URL": "http://www.cdc.gov/mmwr/preview/mmwrhtml/ss6102a1.htm?s_cid=ss6102a1_w&s_cid=cs_281",
        "Volume": "61",
        "Year": "2012",
        "_chapter": "[\"Ch. 17: Southeast and Caribbean FINAL\"]",
        "_record_number": "1863",
        "_uuid": "67150d4c-fc00-4e83-bb2e-9d8a64597173",
        "reftype": "Journal Article"
    },
    "child_publication": "/article/malaria-surveillanceunited-states-2010",
    "href": "http://data.globalchange.gov/reference/67150d4c-fc00-4e83-bb2e-9d8a64597173.json",
    "identifier": "67150d4c-fc00-4e83-bb2e-9d8a64597173",
    "uri": "/reference/67150d4c-fc00-4e83-bb2e-9d8a64597173"
}