{
    "attrs": {
        ".publisher": "Springer Netherlands",
        ".reference_type": "0",
        "Alternate Journal": "Biogeochemistry",
        "Author": "Porter, Ellen M.\rBowman, William D.\rClark, Christopher M.\rCompton, Jana E.\rPardo, Linda H.\rSoong, Jenny L.",
        "DOI": "10.1007/s10533-012-9803-3",
        "Date": "2013/07/01",
        "ISSN": "0168-2563",
        "Issue": "1-3",
        "Journal": "Biogeochemistry",
        "Keywords": "Climate change\rReactive nitrogen\rBiodiversity",
        "Language": "English",
        "Pages": "93-120",
        "Title": "Interactive effects of anthropogenic nitrogen enrichment and climate change on terrestrial and aquatic biodiversity",
        "URL": "http://link.springer.com/content/pdf/10.1007%2Fs10533-012-9803-3.pdf",
        "Volume": "114",
        "Year": "2013",
        "_chapter": "[\"Ch. 15: Biogeochemical FINAL\"]",
        "_record_number": "4613",
        "_uuid": "7daf07ed-8d10-4132-87e5-70e785e35fe1",
        "reftype": "Journal Article"
    },
    "child_publication": "/article/10.1007/s10533-012-9803-3",
    "href": "http://data.globalchange.gov/reference/7daf07ed-8d10-4132-87e5-70e785e35fe1.json",
    "identifier": "7daf07ed-8d10-4132-87e5-70e785e35fe1",
    "uri": "/reference/7daf07ed-8d10-4132-87e5-70e785e35fe1"
}