{
    "attrs": {
        ".reference_type": "10",
        "Author": "DOT,",
        "Institution": "U.S. Department of Transportation, John A. Volpe National Transportation Systems Center",
        "Place Published": "Cambridge, MA",
        "Title": "A framework for considering climate change in transportation and land use scenario planning: final report.  Lessons Learned from an Interagency Pilot Project on Cape Cod.",
        "URL": "http://www.volpe.dot.gov/coi/ppoa/publiclands/projects/docs/cape_cod_pilot_finalreport.pdf",
        "Year": "2011",
        "_chapter": "[\"Ch. 25: Coastal Zone FINAL\"]",
        "_record_number": "735",
        "_uuid": "d5a5c160-7281-4170-90c6-c628d034a5dc",
        "reftype": "Report"
    },
    "child_publication": "/report/dot-framework-2011",
    "href": "http://data.globalchange.gov/reference/d5a5c160-7281-4170-90c6-c628d034a5dc.json",
    "identifier": "d5a5c160-7281-4170-90c6-c628d034a5dc",
    "uri": "/reference/d5a5c160-7281-4170-90c6-c628d034a5dc"
}