{
    "doi": "10.1029/2009JD012442",
    "href": "http://data.globalchange.gov/article/10.1029/2009JD012442.json",
    "identifier": "10.1029/2009JD012442",
    "journal_identifier": "journal-geophysical-research-biogeosciences",
    "journal_pages": "1-21",
    "journal_vol": "115",
    "notes": null,
    "title": "Low-frequency variations in surface atmospheric humidity, temperature, and precipitation: Inferences from reanalyses and monthly gridded observational data sets",
    "uri": "/article/10.1029/2009JD012442",
    "url": null,
    "year": 2010
}