{
    "_public": 1,
    "contact_email": null,
    "contact_note": null,
    "doi": null,
    "frequency": null,
    "href": "http://data.globalchange.gov/report/agnewbeck-strategicmp-2012.json",
    "identifier": "agnewbeck-strategicmp-2012",
    "in_library": null,
    "publication_year": 2012,
    "report_type_identifier": "report",
    "summary": null,
    "title": "Strategic Management Plan: Newtok to Mertarvik",
    "topic": null,
    "uri": "/report/agnewbeck-strategicmp-2012",
    "url": "http://commerce.alaska.gov/dnn/Portals/4/pub/Mertarvik_Strategic_Management_Plan.pdf"
}