{
    "_public": 1,
    "contact_email": null,
    "contact_note": null,
    "doi": null,
    "frequency": null,
    "href": "http://data.globalchange.gov/report/urban-dc-spg-1-2007.json",
    "identifier": "urban-dc-spg-1-2007",
    "in_library": null,
    "publication_year": 2007,
    "report_type_identifier": "report",
    "summary": null,
    "title": "Why Health Insurance is Important. Report No. DC-SPG no. 1",
    "topic": null,
    "uri": "/report/urban-dc-spg-1-2007",
    "url": "http://www.urban.org/UploadedPDF/411569_importance_of_insurance.pdf"
}