{
    "doi": "10.1029/2007JG000453",
    "href": "http://data.globalchange.gov/article/10.1029/2007JG000453.json",
    "identifier": "10.1029/2007JG000453",
    "journal_identifier": "journal-geophysical-research-biogeosciences",
    "journal_pages": null,
    "journal_vol": null,
    "notes": null,
    "title": "Changes in the alpine forest-tundra ecotone commensurate with recent warming in southcentral Alaska: Evidence from orthophotos and field plots",
    "uri": "/article/10.1029/2007JG000453",
    "url": null,
    "year": 2007
}