{
    "_public": 1,
    "contact_email": null,
    "contact_note": null,
    "doi": null,
    "frequency": null,
    "href": "http://data.globalchange.gov/report/usgcrp-nca-ecologicalinidcatorsworkshop-2010.json",
    "identifier": "usgcrp-nca-ecologicalinidcatorsworkshop-2010",
    "in_library": 1,
    "publication_year": 2010,
    "report_type_identifier": "workshop_report",
    "summary": "This workshop focused on developing indicators for ecosystem responses to climate change and integrating observational networks. The workshop was held in Washington, DC on November 30-December 1, 2010.",
    "title": "National Climate Assessment: Ecological Indicators Workshop Report",
    "topic": "Ecosystems,Observing Systems,Indicators",
    "uri": "/report/usgcrp-nca-ecologicalinidcatorsworkshop-2010",
    "url": null
}