{
    "_public": 1,
    "contact_email": null,
    "contact_note": null,
    "doi": null,
    "frequency": null,
    "href": "http://data.globalchange.gov/report/stanfordwie-climadapt-2013.json",
    "identifier": "stanfordwie-climadapt-2013",
    "in_library": null,
    "publication_year": 2013,
    "report_type_identifier": "report",
    "summary": null,
    "title": "Stanford University Climate Adaptation National Poll",
    "topic": null,
    "uri": "/report/stanfordwie-climadapt-2013",
    "url": "http://woods.stanford.edu/research/public-opinion-research/2013-Stanford-Poll-Climate-Adaptation"
}