{
    "_public": 1,
    "contact_email": null,
    "contact_note": null,
    "doi": null,
    "frequency": null,
    "href": "http://data.globalchange.gov/report/noaa-techreport-nesdis-142-5.json",
    "identifier": "noaa-techreport-nesdis-142-5",
    "in_library": null,
    "publication_year": 2013,
    "report_type_identifier": "report",
    "summary": null,
    "title": "Regional Climate Trends and Scenarios for the U.S. National Climate Assessment: Part 5. Climate of the Midwest U.S. NOAA Technical Report NESDIS 142-5",
    "topic": null,
    "uri": "/report/noaa-techreport-nesdis-142-5",
    "url": "http://www.nesdis.noaa.gov/technical_reports/NOAA_NESDIS_Tech_Report_142-5-Climate_of_the_Southwest_U.S.pdf"
}