{
    "attributes": null,
    "cited_by": [],
    "contributors": [
        {
            "href": "http://data.globalchange.gov/contributor/4209.json",
            "id": 4209,
            "organization": {
                "country_code": "US",
                "identifier": "us-forest-service",
                "name": "U.S. Forest Service",
                "organization_type_identifier": "federal",
                "url": "http://www.fs.fed.us/"
            },
            "organization_uri": "/organization/us-forest-service",
            "person": {},
            "person_id": null,
            "person_uri": null,
            "role_type_identifier": "contributing_agency",
            "uri": "/contributor/4209"
        },
        {
            "href": "http://data.globalchange.gov/contributor/4158.json",
            "id": 4158,
            "organization": {
                "country_code": "US",
                "identifier": "us-department-energy",
                "name": "U.S. Department of Energy",
                "organization_type_identifier": "federal",
                "url": "http://www.energy.gov"
            },
            "organization_uri": "/organization/us-department-energy",
            "person": {},
            "person_id": null,
            "person_uri": null,
            "role_type_identifier": "contributing_agency",
            "uri": "/contributor/4158"
        }
    ],
    "create_dt": null,
    "description": "Inside the prototype for SPRUCE experimental chambers. (Credit: DOE) ",
    "figures": [
        {
            "attributes": null,
            "caption": "Inside the prototype for SPRUCE experimental chambers. (Credit: DOE) ",
            "chapter_identifier": "federal-investments-in-global-change-research",
            "create_dt": null,
            "identifier": "experiment-understand-spruce-peatland-responses-climate-change",
            "lat_max": null,
            "lat_min": null,
            "lon_max": null,
            "lon_min": null,
            "ordinal": 5,
            "report_identifier": "usgcrp-ocpfy2015",
            "source_citation": "Spruce and Peatland Responses Under Climatic and Environmental Change, 2010. The SPRUCE experiment, Oak Ridge National Laboratory http://mnspruce.ornl.gov/",
            "submission_dt": null,
            "time_end": null,
            "time_start": null,
            "title": "Experiment to Understand Spruce and Peatland Responses to Climate Change",
            "url": null,
            "usage_limits": "Free to use with credit to the original figure source."
        }
    ],
    "files": [
        {
            "file": "2f/35/9fdfdbc4a3ecdba5a3cf60b47ce3/spruce-exp-chamber-prototype.jpg",
            "href": "http://data.globalchange.gov/assets/2f/35/9fdfdbc4a3ecdba5a3cf60b47ce3/spruce-exp-chamber-prototype.jpg",
            "identifier": "147ebda4-7652-47cb-b8dc-4ab25cf7ae78",
            "landing_page": null,
            "location": null,
            "mime_type": "image/jpeg",
            "sha1": "4bbbf9a57da64f4c9e084c1607ebbbb164dc6af2",
            "size": 369964,
            "thumbnail": "2f/35/9fdfdbc4a3ecdba5a3cf60b47ce3/.thumb-147ebda4-7652-47cb-b8dc-4ab25cf7ae78.png",
            "thumbnail_href": "http://data.globalchange.gov/assets/2f/35/9fdfdbc4a3ecdba5a3cf60b47ce3/.thumb-147ebda4-7652-47cb-b8dc-4ab25cf7ae78.png",
            "uri": "/file/147ebda4-7652-47cb-b8dc-4ab25cf7ae78",
            "url": "/assets/2f/35/9fdfdbc4a3ecdba5a3cf60b47ce3/spruce-exp-chamber-prototype.jpg"
        }
    ],
    "href": "http://data.globalchange.gov/image/aaa4d332-d15b-46f4-b091-8fd7bc9de66a.json",
    "identifier": "aaa4d332-d15b-46f4-b091-8fd7bc9de66a",
    "lat_max": null,
    "lat_min": null,
    "lon_max": null,
    "lon_min": null,
    "parents": [],
    "position": null,
    "references": [],
    "submission_dt": null,
    "time_end": null,
    "time_start": null,
    "title": "Experiment to Understand Spruce and Peatland Responses to Climate Change",
    "uri": "/image/aaa4d332-d15b-46f4-b091-8fd7bc9de66a",
    "url": null,
    "usage_limits": "Free to use with credit to the original figure source."
}