{
    "attrs": {
        ".reference_type": "0",
        "Author": "Fautin, D.\rDalton, P.\rIncze, L.S.\rLeong, J.-A.C.\rPautzke, C.\rRosenberg, A.\rSandifer, P.\rSedberry, G.\rTunnell, J.W., Jr\rAbbott, I.\rBrainard, R.E.\rBrodeur, M.\rEldredge, L. G.\rFeldman, M.\rMoretzsohn, F.\rVroom, P. S.\rWainstein, M.\rWolff, N.",
        "DOI": "10.1371/journal.pone.0011914",
        "ISSN": "1932-6203",
        "Issue": "8",
        "Journal": "PLoS ONE",
        "Pages": "e11914",
        "Title": "An overview of marine biodiversity in United States waters",
        "URL": "http://www.plosone.org/article/info%3Adoi%2F10.1371%2Fjournal.pone.0011914#abstract0",
        "Volume": "5",
        "Year": "2010",
        "_chapter": "[\"Ch. 23: Hawaii FINAL\"]",
        "_record_number": "1239",
        "_uuid": "a9eb9f80-8d41-4304-b596-905ed092bcfe",
        "reftype": "Journal Article"
    },
    "child_publication": "/article/10.1371/journal.pone.0011914",
    "href": "http://data.globalchange.gov/reference/a9eb9f80-8d41-4304-b596-905ed092bcfe.json",
    "identifier": "a9eb9f80-8d41-4304-b596-905ed092bcfe",
    "uri": "/reference/a9eb9f80-8d41-4304-b596-905ed092bcfe"
}