{
    "attrs": {
        ".reference_type": "10",
        "Author": "USFS,",
        "Date": "August 2011",
        "Institution": "U.S. Forest Service, Pacific Northwest Research Station",
        "Pages": "144",
        "Title": "Adapting to Climate Change at Olympic National Forest and Olympic National Park",
        "URL": "http://www.fs.fed.us/pnw/pubs/pnw_gtr844.pdf",
        "Year": "2011",
        "_chapter": "[\"Ch. 28: Adaptation FINAL\"]",
        "_record_number": "4447",
        "_uuid": "6b64c085-f54b-4642-9113-123b66661bac",
        "reftype": "Report"
    },
    "child_publication": "/report/usfs-pnw-gtr-844",
    "href": "http://data.globalchange.gov/reference/6b64c085-f54b-4642-9113-123b66661bac.json",
    "identifier": "6b64c085-f54b-4642-9113-123b66661bac",
    "uri": "/reference/6b64c085-f54b-4642-9113-123b66661bac"
}