{
    "_public": 1,
    "contact_email": null,
    "contact_note": null,
    "doi": null,
    "frequency": null,
    "href": "http://data.globalchange.gov/report/fws-rising-2010.json",
    "identifier": "fws-rising-2010",
    "in_library": null,
    "publication_year": 2010,
    "report_type_identifier": "report",
    "summary": null,
    "title": "Rising to the Urgent Challenge: Strategic Plan for Responding to Accelerating Climate Change",
    "topic": null,
    "uri": "/report/fws-rising-2010",
    "url": "http://www.fws.gov/home/climatechange/pdf/CCStrategicPlan.pdf"
}