{
    "_public": 1,
    "contact_email": null,
    "contact_note": null,
    "doi": null,
    "frequency": null,
    "href": "http://data.globalchange.gov/report/usgcrp-nca-midwestworkshop-2010.json",
    "identifier": "usgcrp-nca-midwestworkshop-2010",
    "in_library": 1,
    "publication_year": 2010,
    "report_type_identifier": "workshop_report",
    "summary": "The first regional and strategic guidance workshops to contribute to the 2013 NCA were held in Chicago in February 2010. ",
    "title": "The National Climate Assessment NCA Report Series, Volume 1. Midwest Regional Workshop: February 22-24, 2010 Chicago, Illinois",
    "topic": null,
    "uri": "/report/usgcrp-nca-midwestworkshop-2010",
    "url": "http://downloads.globalchange.gov/nca/workshop-reports/midwest-regional-workshop-report.pdf"
}