{
    "access_dt": null,
    "attributes": null,
    "cite_metadata": null,
    "data_qualifier": null,
    "description": "ABSTRACT: Not available.",
    "description_attribution": "http://daac.ornl.gov//LBA/guides/ND11_Veg_Biomass_MT.html",
    "doi": "10.3334/ORNLDAAC/964",
    "end_time": "2004-07-20T00:00:00",
    "href": "http://data.globalchange.gov/dataset/nasa-ornldaac-964.json",
    "identifier": "nasa-ornldaac-964",
    "lat_max": "-10.4249",
    "lat_min": "-10.4249",
    "lon_max": "-58.7597",
    "lon_min": "-58.7597",
    "name": "LBA-ECO ND-11 Ecotone Vegetation Survey and Biomass, NW Mato Grosso, Brazil: 2004",
    "native_id": "ND11_ECOTONE_VEG",
    "processing_level": null,
    "publication_year": null,
    "release_dt": "2010-01-01T00:00:00",
    "scale": null,
    "scope": null,
    "spatial_extent": null,
    "spatial_ref_sys": null,
    "spatial_res": null,
    "start_time": "2004-06-05T00:00:00",
    "temporal_extent": null,
    "temporal_resolution": null,
    "type": null,
    "uri": "/dataset/nasa-ornldaac-964",
    "url": "http://daac.ornl.gov/cgi-bin/dsviewer.pl?ds_id=964",
    "variables": null,
    "version": null,
    "vertical_extent": null
}