{
    "access_dt": null,
    "attributes": null,
    "cite_metadata": null,
    "data_qualifier": null,
    "description": "This data set shows the modeled surface temperature reconstruction from an inversion of the 300 m WDC05A borehole at the West Antarctic Divide Ice core site.",
    "description_attribution": null,
    "doi": "10.7265/N56971HF",
    "end_time": null,
    "href": "http://data.globalchange.gov/dataset/nsidc-0638.json",
    "identifier": "nsidc-0638",
    "lat_max": "-79.463",
    "lat_min": "-79.463",
    "lon_max": "-112.125",
    "lon_min": "-112.125",
    "name": "Surface Temperature Reconstruction from Borehole Temperature Measurement in WDC05A",
    "native_id": "NSIDC-0638",
    "processing_level": null,
    "publication_year": null,
    "release_dt": "2015-06-09T00:00:00",
    "scale": null,
    "scope": null,
    "spatial_extent": null,
    "spatial_ref_sys": null,
    "spatial_res": null,
    "start_time": null,
    "temporal_extent": null,
    "temporal_resolution": null,
    "type": null,
    "uri": "/dataset/nsidc-0638",
    "url": "http://nsidc.org/data/NSIDC-0638",
    "variables": null,
    "version": null,
    "vertical_extent": null
}