{
    "attrs": {
        "Author": "Vantuono, W.C.",
        "E-Pub Date": "October 31, 2012",
        "Issue": null,
        "Periodical Title": "Railway Age",
        "Place Published": "Chicago, IL",
        "Publisher": "Simmons-Boardman Publishing, Inc.",
        "Title": "Hurricane Sandy Devastates NY/NJ area passenger rail systems",
        "URL": "http://www.railwayage.com/index.php/passenger/commuter-regional/hurricane-sandy-devastates-ny-nj-area-passenger-rail-systems.html",
        "Year": "2012",
        "reftype": "Electronic Article"
    },
    "href": "http://data.globalchange.gov/generic/52e70a38-c5ae-41cc-99a3-1cb319b7e74b.json",
    "identifier": "52e70a38-c5ae-41cc-99a3-1cb319b7e74b",
    "uri": "/generic/52e70a38-c5ae-41cc-99a3-1cb319b7e74b"
}