{
    "attrs": {
        ".reference_type": "0",
        "Author": "Delfino, R.J.\rBrummel, S.\rWu, J.\rStern, H.\rOstro, B.\rLipsett, M.\rWiner, A.\rStreet, D.H.\rZhang, L.\rTjoa, T.\rGillen, D.L.",
        "DOI": "10.1136/oem.2008.041376",
        "ISSN": "1470-7926",
        "Issue": "3",
        "Journal": "Occupational and Environmental Medicine",
        "Pages": "189-197",
        "Title": "The relationship of respiratory and cardiovascular hospital admissions to the southern California wildfires of 2003",
        "URL": "[http://oem.bmj.com/content/66/3/189.full.pdf+html",
        "Volume": "66",
        "Year": "2009",
        "_chapter": "[\"Ch. 9: Human Health FINAL\",\"Ch. 17: Southeast and Caribbean FINAL\",\"Overview\"]",
        "_record_number": "1427",
        "_uuid": "1a72beb2-f4a0-4db9-bac8-eac55cbf676d",
        "reftype": "Journal Article"
    },
    "child_publication": "/article/10.1136/oem.2008.041376",
    "href": "http://data.globalchange.gov/reference/1a72beb2-f4a0-4db9-bac8-eac55cbf676d.json",
    "identifier": "1a72beb2-f4a0-4db9-bac8-eac55cbf676d",
    "uri": "/reference/1a72beb2-f4a0-4db9-bac8-eac55cbf676d"
}