{
    "attrs": {
        ".reference_type": "0",
        "Author": "Balan Sarojini, Beena\rStott, Peter A.\rBlack, Emily\rPolson, Debbie",
        "DOI": "10.1029/2012GL053373",
        "ISSN": "1944-8007",
        "Issue": "21",
        "Journal": "Geophysical Research Letters",
        "Keywords": "anthropogenic climate change\rdetection and attribution\rglobal climate models\robservations\rprecipitation\r1626 Global climate models\r1635 Oceans\r1637 Regional climate change\r1655 Water cycles\r1854 Precipitation",
        "Pages": "L21706",
        "Title": "Fingerprints of changes in annual and seasonal precipitation from CMIP5 models over land and ocean",
        "URL": "http://onlinelibrary.wiley.com/doi/10.1029/2012GL053373/pdf",
        "Volume": "39",
        "Year": "2012",
        "_chapter": "[\"Ch. 2: Our Changing Climate FINAL\"]",
        "_record_number": "4687",
        "_uuid": "32f3d1fd-faa0-402a-b55c-6560b851c487",
        "reftype": "Journal Article"
    },
    "child_publication": "/article/10.1029/2012GL053373",
    "href": "http://data.globalchange.gov/reference/32f3d1fd-faa0-402a-b55c-6560b851c487.json",
    "identifier": "32f3d1fd-faa0-402a-b55c-6560b851c487",
    "uri": "/reference/32f3d1fd-faa0-402a-b55c-6560b851c487"
}