{
    "attrs": {
        ".reference_type": "0",
        "Author": "Knutson, C.L.\rHaigh, T.\rHayes, M.J.\rWidhalm, M.\rNothwehr, J.\rKleinschmidt, M.\rGraf, L.",
        "DOI": "10.1017/S174217051100010X",
        "ISSN": "1742-1713",
        "Issue": "3",
        "Journal": "Renewable Agriculture and Food Systems",
        "Pages": "255-266",
        "Title": "Farmer perceptions of sustainable agriculture practices and drought risk reduction in Nebraska, USA",
        "Volume": "26",
        "Year": "2011",
        "_chapter": "[\"Ch. 6: Agriculture FINAL\"]",
        "_record_number": "691",
        "_uuid": "9d4df4d1-ebf3-4fd3-88e3-3b951e2ced06",
        "reftype": "Journal Article"
    },
    "child_publication": "/article/10.1017/S174217051100010X",
    "href": "http://data.globalchange.gov/reference/9d4df4d1-ebf3-4fd3-88e3-3b951e2ced06.json",
    "identifier": "9d4df4d1-ebf3-4fd3-88e3-3b951e2ced06",
    "uri": "/reference/9d4df4d1-ebf3-4fd3-88e3-3b951e2ced06"
}