{
    "attrs": {
        ".reference_type": "1",
        "Author": "Linkov, I.\rMoberg, E.",
        "ISBN": "1439853185",
        "Number of Pages": "186",
        "Place Published": "Boca Raton, FL",
        "Publisher": "CRC Press Taylor & Francis Group",
        "Reviewer": "0023e650-9534-4fb9-be44-fa3f55f0babe",
        "Series Editor": "Suter, G.W.",
        "Title": "Multi-Criteria Decision Analysis: Environmental Applications and Case Studies",
        "Year": "2011",
        "_chapter": "[\"Ch. 26: Decision Support FINAL\"]",
        "_record_number": "1136",
        "_uuid": "0023e650-9534-4fb9-be44-fa3f55f0babe",
        "reftype": "Book"
    },
    "child_publication": "/book/ae257d61-4ae0-431a-8460-0b5c66bc8b48",
    "href": "http://data.globalchange.gov/reference/0023e650-9534-4fb9-be44-fa3f55f0babe.json",
    "identifier": "0023e650-9534-4fb9-be44-fa3f55f0babe",
    "uri": "/reference/0023e650-9534-4fb9-be44-fa3f55f0babe"
}