{
    "attrs": {
        ".publisher": "Ecological Society of America",
        ".reference_type": "0",
        "Access Date": "2012/02/24",
        "Author": "McKinley, Duncan C.\rRyan, Michael G.\rBirdsey, Richard A.\rGiardina, Christian P.\rHarmon, Mark E.\rHeath, Linda S.\rHoughton, Richard A.\rJackson, Robert B.\rMorrison, James F.\rMurray, Brian C.\rPataki, Diane E.\rSkog, Kenneth E.",
        "DOI": "10.1890/10-0697.1",
        "Date": "2011/09/01",
        "ISSN": "1051-0761",
        "Issue": "6",
        "Journal": "Ecological Applications",
        "Pages": "1902-1924",
        "Title": "A synthesis of current knowledge on forests and carbon storage in the United States",
        "URL": "http://128.104.77.228/documnts/pdf2011/fpl_2011_mckinley001.pdf",
        "Volume": "21",
        "Year": "2011",
        "_chapter": "[\"Ch. 7: Forests FINAL\"]",
        "_record_number": "1954",
        "_uuid": "e25be0f6-adbc-4a5b-a614-db2dea9ee409",
        "reftype": "Journal Article"
    },
    "child_publication": "/article/10.1890/10-0697.1",
    "href": "http://data.globalchange.gov/reference/e25be0f6-adbc-4a5b-a614-db2dea9ee409.json",
    "identifier": "e25be0f6-adbc-4a5b-a614-db2dea9ee409",
    "uri": "/reference/e25be0f6-adbc-4a5b-a614-db2dea9ee409"
}