{
    "attrs": {
        ".reference_type": "0",
        "Author": "Hellmann, J.J.\rNadelhoffer, K.J.\rIverson, L.R.\rZiska, L. H.\rMatthews, S.N.\rMyers, P.\rPrasad, A.M.\rPeters, M.P.",
        "DOI": "10.1016/j.jglr.2009.12.001",
        "Date": "2010",
        "ISSN": "0380-1330",
        "Issue": "Supplement 2",
        "Journal": "Great Lakes Research",
        "Keywords": "Climate Change; CV paper",
        "Label": "16430",
        "Pages": "74-85",
        "Title": "Climate change impacts on terrestrial ecosystems in the Chicago region",
        "URL": "http://naldc.nal.usda.gov/download/49775/PDF",
        "Volume": "36",
        "Year": "2010",
        "_chapter": "[\"Ch. 18: Midwest FINAL\"]",
        "_record_number": "312",
        "_uuid": "fa801dec-cb80-491f-b9d9-3489236e4b6d",
        "reftype": "Journal Article"
    },
    "child_publication": "/article/10.1016/j.jglr.2009.12.001",
    "href": "http://data.globalchange.gov/reference/fa801dec-cb80-491f-b9d9-3489236e4b6d.json",
    "identifier": "fa801dec-cb80-491f-b9d9-3489236e4b6d",
    "uri": "/reference/fa801dec-cb80-491f-b9d9-3489236e4b6d"
}