{
    "attrs": {
        ".reference_type": "0",
        "Author": "Sandstrom, M.A.\rLauritsen, R.G.\rChangnon, D.",
        "DOI": "10.2747/0272-3646.25.3.191",
        "ISSN": "0272-3646",
        "Issue": "3",
        "Journal": "Physical Geography",
        "Pages": "191-207",
        "Title": "A central-US summer extreme dew-point climatology (1949-2000)",
        "Volume": "25",
        "Year": "2004",
        "_chapter": "[\"Ch. 13: Land Use and Land Cover Change FINAL\"]",
        "_record_number": "2742",
        "_uuid": "5a030fd6-b86b-4204-be8f-767e0d149bde",
        "reftype": "Journal Article"
    },
    "child_publication": "/article/10.2747/0272-3646.25.3.191",
    "href": "http://data.globalchange.gov/reference/5a030fd6-b86b-4204-be8f-767e0d149bde.json",
    "identifier": "5a030fd6-b86b-4204-be8f-767e0d149bde",
    "uri": "/reference/5a030fd6-b86b-4204-be8f-767e0d149bde"
}