{
    "attrs": {
        ".reference_type": "0",
        "Author": "Moore, B., III\rBraswell, B.H.",
        "DOI": "10.1029/93GB03392",
        "Issue": "1",
        "Journal": "Global Biogeochemical Cycles",
        "Pages": "23-38",
        "Title": "The lifetime of excess atmospheric carbon dioxide",
        "Volume": "8",
        "Year": "1994",
        "_chapter": "[\"Ch. 27: Mitigation FINAL\"]",
        "_record_number": "2073",
        "_uuid": "eb18eac2-1dac-46f8-8d14-8c62299e72a3",
        "reftype": "Journal Article"
    },
    "child_publication": "/article/10.1029/93GB03392",
    "href": "http://data.globalchange.gov/reference/eb18eac2-1dac-46f8-8d14-8c62299e72a3.json",
    "identifier": "eb18eac2-1dac-46f8-8d14-8c62299e72a3",
    "uri": "/reference/eb18eac2-1dac-46f8-8d14-8c62299e72a3"
}